{
    "CampaignConfig": {
        "ID": "Story_Campaign_Config_ID",
        "Version": 1,
        "Name": "ELI-427-04-Iteration-Config-Name",
        "Type": "V",
        "Target": "FLU",
        "Manager": [
            "person1@nhs.net"
        ],
        "Approver": [
            "person1@nhs.net"
        ],
        "Reviewer": [
            "person1@nhs.net"
        ],
        "IterationFrequency": "X",
        "IterationType": "O",
        "IterationTime": "07:00:00",
        "StartDate": "20250717",
        "EndDate": "20350717",
        "ApprovalMinimum": 0,
        "ApprovalMaximum": 0,
        "DefaultCommsRouting": "TEST_ACTION",
        "Iterations": [
            {
                "ID": "AUTO_RSV_ELI-427-04-Iteration-ID",
                "DefaultCommsRouting": "TEST_ACTION",
                "DefaultNotActionableRouting": "TEST_NOT_ACTION",
                "DefaultNotEligibleRouting": "TEST_NOT_ELI",
                "Version": 1,
                "Name": "ELI-427-04-Iteration-Config-Name",
                "IterationDate": "20240808",
                "IterationNumber": 1,
                "CommsType": "I",
                "ApprovalMinimum": 0,
                "ApprovalMaximum": 0,
                "Type": "O",
                "StatusText": {
                    "Actionable": ""
                },
                "IterationCohorts": [
                    {
                        "CohortLabel": "eli_427_cohort_1",
                        "CohortGroup": "eli_427_cohort_group_1",
                        "PositiveDescription": "In eli_427_cohort_1",
                        "NegativeDescription": "Not in eli_427_cohort_1",
                        "Priority": 1
                    }
                ],
                "IterationRules": [
                    {
                        "Type": "F",
                        "Name": "Remove under 74 Years on day of execution",
                        "Description": "Filter out anyone who is not 74 years old.",
                        "Priority": 100,
                        "AttributeLevel": "PERSON",
                        "AttributeName": "DATE_OF_BIRTH",
                        "Operator": "Y>",
                        "Comparator": "-74"
                    },
                    {
                        "Type": "F",
                        "Name": "Remove under 75 Years on day of execution",
                        "Description": "Filter out anyone who is not 74 years old.",
                        "Priority": 101,
                        "AttributeLevel": "PERSON",
                        "AttributeName": "DATE_OF_BIRTH",
                        "Operator": "Y<",
                        "Comparator": "-74"
                    },
                    {
                        "Type": "S",
                        "Name": "AlreadyVaccinated",
                        "Description": "## You've had your RSV vaccination.",
                        "Priority": 200,
                        "AttributeLevel": "TARGET",
                        "AttributeTarget": "RSV",
                        "AttributeName": "LAST_SUCCESSFUL_DATE",
                        "Operator": "is_not_empty",
                        "Comparator": ""
                    }
                ],
                "ActionsMapper": {
                    "TEST_ACTION": {
                        "ExternalRoutingCode": "TestAction",
                        "ActionDescription": "TestAction Description",
                        "ActionType": "ButtonWithAuthLink",
                        "UrlLink": "http://www.nhs.uk/book-rsv",
                        "UrlLabel": "Continue to booking"
                    },
                    "TEST_NOT_ACTION": {
                        "ExternalRoutingCode": "TestNotAction",
                        "ActionDescription": "TestNotAction Description",
                        "ActionType": "ButtonWithAuthLink",
                        "UrlLink": null,
                        "UrlLabel": ""
                    },
                    "TEST_NOT_ELI": {
                        "ExternalRoutingCode": "TestNotEli",
                        "ActionDescription": "TestNotEli Description",
                        "ActionType": "",
                        "UrlLink": null,
                        "UrlLabel": ""
                    }
                }
            }
        ]
    }
}
